ryf/__init__.py
ryf-0.5.data/scripts/comp.py
ryf-0.5.data/scripts/ryf
ryf-0.5.data/scripts/ryf.py
ryf-0.5.dist-info/METADATA
ryf-0.5.dist-info/WHEEL
ryf-0.5.dist-info/top_level.txt
ryf-0.5.dist-info/RECORD
