Metadata-Version: 2.1
Name: ryf
Version: 0.5
Summary: A programming language written in python
Home-page: https://github.com/bm20894/ryf
Author: Miles Boswell
Author-email: milesboz@me.com
License: UNKNOWN
Platform: UNKNOWN
Classifier: Programming Language :: Python :: 3
